kmeans/__init__.py
kmeans/kmeans.py
MyAlgorithms-0.0.2.dist-info/LICENSE
MyAlgorithms-0.0.2.dist-info/METADATA
MyAlgorithms-0.0.2.dist-info/WHEEL
MyAlgorithms-0.0.2.dist-info/top_level.txt
MyAlgorithms-0.0.2.dist-info/RECORD
